{
    "pageProps": {
        "candidate": {
            "id": 6,
            "name": "พิศาล กิตติเยาวมาลย์",
            "number": 6,
            "sex": "male",
            "age": 76,
            "birthdate": "1949-09-28",
            "higher_education": "ปริญญาตรี",
            "career": "อื่นๆ",
            "political_career": "-",
            "party": "อิสระ",
            "highlight": false,
            "cover_pic": "/candidate/static/images/og/06-3.jpg",
            "profile_pic": "/candidate/static/images/og/06-2.jpg",
            "disqualified": null
        },
        "isComingSoon": false
    },
    "__N_SSG": true
}